flix_cli/__init__.py
flix_cli/__main__.py
flix_cli/core/__flix_cli__.py
flix_cli/core/__init__.py
flix_cli/core/__version__.py
flix_cli/core/utils/__cast__.py
flix_cli/core/utils/__config__.py
flix_cli/core/utils/__decryptor__.py
flix_cli/core/utils/__downloader__.py
flix_cli/core/utils/__player__.py
flix_cli/core/utils/test.py
flix_cli-1.8.1.17.dist-info/METADATA
flix_cli-1.8.1.17.dist-info/WHEEL
flix_cli-1.8.1.17.dist-info/entry_points.txt
flix_cli-1.8.1.17.dist-info/licenses/LICENSE
flix_cli-1.8.1.17.dist-info/RECORD
