Metadata-Version: 2.4
Name: flix-cli
Version: 1.8.1.17
Summary: A high efficient, powerful and fast movie scraper.
Author-email: DemonKingSwarn <swarn@demonkingswarn.live>
License: GPLv3
License-File: LICENSE
Requires-Python: >=3.11
Requires-Dist: beautifulsoup4==4.10.0
Requires-Dist: catt==0.13.1
Requires-Dist: httpx==0.28.1
Requires-Dist: krfzf-py==0.0.4
Requires-Dist: platformdirs==4.5.0
Requires-Dist: regex==2025.9.1
Requires-Dist: typer==0.20.0
Requires-Dist: yt-dlp>=2025.10.22
Provides-Extra: dev
